[{
  "_id": {
    "$oid": "66068b6014366356afb716c9"
  },
  "flightNumber": "TDB123",
  "destination": "Los Angeles",
  "date": "2024-03-17",
  "departure Time": "08:00",
  "estimated Departure Time": "08:15",
  "status": "Delayed",
  "gate": "A1",
  "airline": "Delta",
  "terminal": "Terminal 1",
  "remarks": "Due to weather conditions"
},
{
  "_id": {
    "$oid": "66068b6014366356afb716ca"
  },
  "flightNumber": "UAI456",
  "destination": "Chicago",
  "date": "2024-03-17",
  "departure Time": "09:30",
  "estimated Departure Time": "09:45",
  "status": "Departed",
  "gate": "B3",
  "airline": "American Airlines",
  "terminal": "Terminal 2",
  "remarks": "None"
},
{
  "_id": {
    "$oid": "66068b6014366356afb716cb"
  },
  "flightNumber": "OPK789",
  "destination": "London",
  "date": "2024-03-17",
  "departure Time": "10:45",
  "estimated Departure Time": "11:00",
  "status": "Delayed",
  "gate": "C2",
  "airline": "United Airlines",
  "terminal": "Terminal 3",
  "remarks": "Technical issues"
},
{
  "_id": {
    "$oid": "66068b6014366356afb716cc"
  },
  "flightNumber": "UYR101",
  "destination": "Tokyo",
  "date": "2024-03-17",
  "departure Time": "12:15",
  "estimated Departure Time": "12:30",
  "status": "Departed",
  "gate": "D4",
  "airline": "British Airways",
  "terminal": "Terminal 4",
  "remarks": "None"
},
{
  "_id": {
    "$oid": "66068b6014366356afb716cd"
  },
  "flightNumber": "OIJ202",
  "destination": "Paris",
  "date": "2024-03-17",
  "departure Time": "13:45",
  "estimated Departure Time": "14:00",
  "status": "Delayed",
  "gate": "E5",
  "airline": "Japan Airlines",
  "terminal": "International Terminal",
  "remarks": "Air traffic congestion"
},
{
  "_id": {
    "$oid": "66068b6014366356afb716ce"
  },
  "flightNumber": "QUY303",
  "destination": "Sydney",
  "date": "2024-03-17",
  "departure Time": "15:20",
  "estimated Departure Time": "15:35",
  "status": "Delayed",
  "gate": "F6",
  "airline": "Air France",
  "terminal": "Terminal 5",
  "remarks": "Security check delay"
},
{
  "_id": {
    "$oid": "66068b6014366356afb716cf"
  },
  "flightNumber": "MKD404",
  "destination": "Dubai",
  "date": "2024-03-17",
  "departure Time": "16:40",
  "estimated Departure Time": "16:55",
  "status": "Departed",
  "gate": "G7",
  "airline": "Qantas",
  "terminal": "International Terminal",
  "remarks": "None"
},
{
  "_id": {
    "$oid": "66068b6014366356afb716d0"
  },
  "flightNumber": "FHJ505",
  "destination": "Beijing",
  "date": "2024-03-17",
  "departure Time": "18:10",
  "estimated Departure Time": "18:25",
  "status": "Departed",
  "gate": "H8",
  "airline": "Emirates",
  "terminal": "Terminal 6",
  "remarks": "None"
},
{
  "_id": {
    "$oid": "66068b6014366356afb716d1"
  },
  "flightNumber": "RHY606",
  "destination": "Moscow",
  "date": "2024-03-17",
  "departure Time": "19:30",
  "estimated Departure Time": "19:45",
  "status": "Delayed",
  "gate": "I9",
  "airline": "Air China",
  "terminal": "International Terminal",
  "remarks": "Weather conditions"
},
{
  "_id": {
    "$oid": "66068b6014366356afb716d2"
  },
  "flightNumber": "CYH707",
  "destination": "Berlin",
  "date": "2024-03-17",
  "departure Time": "20:55",
  "estimated Departure Time": "21:10",
  "status": "Departed",
  "gate": "J10",
  "airline": "Aeroflot",
  "terminal": "Terminal 7",
  "remarks": "None"
},
{
  "_id": {
    "$oid": "66068b6014366356afb716d3"
  },
  "flightNumber": "ZHX808",
  "destination": "Rome",
  "date": "2024-03-17",
  "departure Time": "22:20",
  "estimated Departure Time": "22:35",
  "status": "Delayed",
  "gate": "K11",
  "airline": "Lufthansa",
  "terminal": "Terminal 8",
  "remarks": "Technical maintenance"
},
{
  "_id": {
    "$oid": "66068b6014366356afb716d4"
  },
  "flightNumber": "ABC101",
  "destination": "New York",
  "date": "2024-03-18",
  "departure Time": "08:30",
  "estimated Departure Time": "08:30",
  "status": "On Time",
  "gate": "A2",
  "airline": "Delta",
  "terminal": "Terminal 1",
  "remarks": "Technical issues"
},
{
  "_id": {
    "$oid": "66068b6014366356afb716d5"
  },
  "flightNumber": "XYZ202",
  "destination": "Tokyo",
  "date": "2024-03-18",
  "departure Time": "09:45",
  "estimated Departure Time": "09:45",
  "status": "On Time",
  "gate": "B4",
  "airline": "Japan Airlines",
  "terminal": "Terminal 2",
  "remarks": "None"
},
{
  "_id": {
    "$oid": "66068b6014366356afb716d6"
  },
  "flightNumber": "PQR303",
  "destination": "Singapore",
  "date": "2024-03-18",
  "departure Time": "11:15",
  "estimated Departure Time": "11:15",
  "status": "On Time",
  "gate": "C6",
  "airline": "Singapore Airlines",
  "terminal": "Terminal 3",
  "remarks": "Air traffic congestion"
},
{
  "_id": {
    "$oid": "66068b6014366356afb716d7"
  },
  "flightNumber": "DEF404",
  "destination": "Sydney",
  "date": "2024-03-18",
  "departure Time": "13:00",
  "estimated Departure Time": "13:00",
  "status": "On Time",
  "gate": "D8",
  "airline": "Qantas",
  "terminal": "Terminal 4",
  "remarks": "None"
},
{
  "_id": {
    "$oid": "66068b6014366356afb716d8"
  },
  "flightNumber": "GHI505",
  "destination": "Paris",
  "date": "2024-03-18",
  "departure Time": "14:30",
  "estimated Departure Time": "14:30",
  "status": "On Time",
  "gate": "E10",
  "airline": "Air France",
  "terminal": "International Terminal",
  "remarks": "Weather conditions"
},
{
  "_id": {
    "$oid": "66068b6014366356afb716d9"
  },
  "flightNumber": "JKL606",
  "destination": "London",
  "date": "2024-03-18",
  "departure Time": "16:00",
  "estimated Departure Time": "16:00",
  "status": "On Time",
  "gate": "F12",
  "airline": "British Airways",
  "terminal": "Terminal 5",
  "remarks": "None"
},
{
  "_id": {
    "$oid": "66068b6014366356afb716da"
  },
  "flightNumber": "MNO707",
  "destination": "Dubai",
  "date": "2024-03-18",
  "departure Time": "17:45",
  "estimated Departure Time": "17:45",
  "status": "On Time",
  "gate": "G14",
  "airline": "Emirates",
  "terminal": "Terminal 6",
  "remarks": "None"
},
{
  "_id": {
    "$oid": "66068b6014366356afb716db"
  },
  "flightNumber": "QRS808",
  "destination": "Beijing",
  "date": "2024-03-18",
  "departure Time": "19:20",
  "estimated Departure Time": "19:20",
  "status": "On Time",
  "gate": "H16",
  "airline": "Air China",
  "terminal": "International Terminal",
  "remarks": "Security check delay"
},
{
  "_id": {
    "$oid": "66068b6014366356afb716dc"
  },
  "flightNumber": "TUV909",
  "destination": "Berlin",
  "date": "2024-03-18",
  "departure Time": "20:55",
  "estimated Departure Time": "20:55",
  "status": "On Time",
  "gate": "J18",
  "airline": "Lufthansa",
  "terminal": "Terminal 7",
  "remarks": "None"
},
{
  "_id": {
    "$oid": "66068b6014366356afb716dd"
  },
  "flightNumber": "WXY010",
  "destination": "Moscow",
  "date": "2024-03-18",
  "departure Time": "12:30",
  "estimated Departure Time": "23:45",
  "status": "Delayed",
  "gate": "K20",
  "airline": "Aeroflot",
  "terminal": "Terminal 8",
  "remarks": "Technical maintenance"
}]